[
    {
        "rule": "43",
        "测试关注点": "采用匹配成交方式的债券交易时间",
        "testid": "43.1",
        "交易市场": "上海证券交易所",
        "成交方式": "匹配成交",
        "交易品种": "债券",
        "操作": "申报",
        "结果": "成功",
        "时间": "9:15至9:25",
        "交易方向": "买入"
    },
    {
        "rule": "43",
        "测试关注点": "采用匹配成交方式的债券交易时间",
        "testid": "43.2",
        "交易市场": "上海证券交易所",
        "成交方式": "匹配成交",
        "交易品种": "债券",
        "操作": "申报",
        "结果": "成功",
        "时间": "9:30至11:30、13:00至15:30",
        "交易方向": "卖出"
    },
    {
        "rule": "43",
        "测试关注点": "采用点击成交方式的债券交易时间",
        "testid": "43.3",
        "交易市场": "上海证券交易所",
        "成交方式": "点击成交",
        "交易品种": "债券",
        "操作": "申报",
        "结果": "成功",
        "时间": "9:00至11:30、13:00至20:00"
    },
    {
        "rule": "43",
        "测试关注点": "采用协商成交方式的债券交易时间",
        "testid": "43.4",
        "交易市场": "上海证券交易所",
        "成交方式": "协商成交",
        "交易品种": "债券",
        "操作": "申报",
        "结果": "成功",
        "时间": "9:00至11:30、13:00至20:00"
    },
    {
        "rule": "43",
        "测试关注点": "采用询价成交方式的债券交易时间",
        "testid": "43.5",
        "交易市场": "上海证券交易所",
        "成交方式": "询价成交",
        "交易品种": "债券",
        "操作": "申报",
        "结果": "成功",
        "时间": "9:00至11:30、13:00至20:00"
    },
    {
        "rule": "43",
        "测试关注点": "采用竞买成交方式的债券交易时间",
        "testid": "43.6",
        "交易市场": "上海证券交易所",
        "成交方式": "竞买成交",
        "交易品种": "债券",
        "操作": "申报",
        "结果": "成功",
        "时间": "9:00至10:00",
        "交易方向": "卖出"
    },
    {
        "rule": "43",
        "测试关注点": "采用竞买成交方式的债券交易时间",
        "testid": "43.7",
        "交易市场": "上海证券交易所",
        "成交方式": "竞买成交",
        "交易品种": "债券",
        "操作": "申报",
        "结果": "成功",
        "时间": "10:00至11:30",
        "交易方向": "买入"
    },
    {
        "rule": "53",
        "测试关注点": "用匹配成交方式的债券现券的申报数量限制",
        "testid": "53.1",
        "交易市场": "上海证券交易所",
        "交易类型": "债券现券",
        "成交方式": "匹配成交",
        "申报数量": "申报数量应当为10万元面额或者其整数倍",
        "操作": "申报买入",
        "前置规则": "53.17",
        "结果": "成功"
    },
    {
        "rule": "53",
        "测试关注点": "用匹配成交方式的债券现券的申报数量限制",
        "testid": "53.2",
        "交易市场": "上海证券交易所",
        "交易类型": "债券现券",
        "成交方式": "匹配成交",
        "申报数量": "卖出时不足10万元面额的部分,应当一次性申报",
        "操作": "申报卖出",
        "前置规则": "53.17",
        "结果": "成功"
    },
    {
        "rule": "53",
        "测试关注点": "用匹配成交方式的债券现券的申报数量限制",
        "testid": "53.3",
        "交易市场": "上海证券交易所",
        "交易类型": "债券现券",
        "成交方式": "匹配成交",
        "申报数量": "不是10万元面额或者其整数倍",
        "操作": "申报买入",
        "结果": "不成功"
    },
    {
        "rule": "53",
        "测试关注点": "用匹配成交方式的债券现券的申报数量限制",
        "testid": "53.4",
        "交易市场": "上海证券交易所",
        "交易类型": "债券现券",
        "成交方式": "匹配成交",
        "申报数量": "卖出时超过10万元面额",
        "前置规则": "53.17",
        "操作": "申报卖出",
        "结果": "成功"
    },
    {
        "rule": "53",
        "测试关注点": "债券通用质押式回购的申报数量限制",
        "testid": "53.5",
        "交易市场": "上海证券交易所",
        "成交方式": "匹配成交",
        "交易类型": "债券通用质押式回购",
        "申报数量": "申报数量应当为1000元面额或者其整数倍",
        "操作": "申报",
        "前置规则": "53.17",
        "结果": "成功"
    },
    {
        "rule": "53",
        "测试关注点": "债券通用质押式回购的申报数量限制",
        "testid": "53.6",
        "交易市场": "上海证券交易所",
        "成交方式": "匹配成交",
        "交易类型": "债券通用质押式回购",
        "申报数量": "非1000元面额或者其整数倍",
        "操作": "申报",
        "结果": "不成功"
    },
    {
        "rule": "53",
        "测试关注点": "用点击成交方式的债券现券的申报数量限制",
        "testid": "53.7",
        "交易市场": "上海证券交易所",
        "成交方式": "点击成交",
        "申报数量": "申报数量应当为10万元面额或者其整数倍",
        "操作": "申报",
        "前置规则": "53.17",
        "结果": "成功"
    },
    {
        "rule": "53",
        "测试关注点": "用点击成交方式的债券现券的申报数量限制",
        "testid": "53.8",
        "交易市场": "上海证券交易所",
        "成交方式": "点击成交",
        "申报数量": "申报数量不是10万元面额或者其整数倍",
        "操作": "申报",
        "结果": "不成功"
    },
    {
        "rule": "53",
        "测试关注点": "用询价成交方式的债券现券的申报数量限制",
        "testid": "53.9",
        "交易市场": "上海证券交易所",
        "成交方式": "询价成交",
        "申报数量": "不低于10万元面额,且为1000元面额的整数倍",
        "操作": "申报",
        "前置规则": "53.17",
        "结果": "成功"
    },
    {
        "rule": "53",
        "测试关注点": "用询价成交方式的债券现券的申报数量限制",
        "testid": "53.10",
        "交易市场": "上海证券交易所",
        "成交方式": "询价成交",
        "申报数量": "低于10万元面额,且为1000元面额的整数倍",
        "操作": "申报",
        "结果": "不成功"
    },
    {
        "rule": "53",
        "测试关注点": "用竞买成交方式的债券现券的申报数量限制",
        "testid": "53.11",
        "交易市场": "上海证券交易所",
        "成交方式": "竞买成交",
        "申报数量": "不低于10万元面额,且为1000元面额的整数倍",
        "操作": "申报",
        "前置规则": "53.17",
        "结果": "成功"
    },
    {
        "rule": "53",
        "测试关注点": "用竞买成交方式的债券现券的申报数量限制",
        "testid": "53.12",
        "交易市场": "上海证券交易所",
        "成交方式": "竞买成交",
        "申报数量": "低于10万元面额,且为1000元面额的整数倍",
        "操作": "申报",
        "结果": "不成功"
    },
    {
        "rule": "53",
        "测试关注点": "用协商成交方式的债券现券的申报数量限制",
        "testid": "53.13",
        "交易市场": "上海证券交易所",
        "成交方式": "协商成交",
        "交易类型": "债券现券",
        "申报数量": "不低于1000元面额,且为100元面额整数倍",
        "操作": "申报",
        "前置规则": "53.17",
        "结果": "成功"
    },
    {
        "rule": "53",
        "测试关注点": "用协商成交方式的债券现券的申报数量限制",
        "testid": "53.14",
        "交易市场": "上海证券交易所",
        "成交方式": "协商成交",
        "交易类型": "债券现券",
        "申报数量": "低于1000元面额,且为100元面额整数倍",
        "操作": "申报",
        "结果": "不成功"
    },
    {
        "rule": "53",
        "测试关注点": "用协商成交方式的债券通用质押式回购的申报数量限制",
        "testid": "53.15",
        "交易市场": "上海证券交易所",
        "成交方式": "协商成交",
        "交易类型": "债券通用质押式回购",
        "申报数量": "为1000元面额或者其整数倍",
        "操作": "申报",
        "结果": "成功",
        "前置规则": "53.17"
    },
    {
        "rule": "53",
        "测试关注点": "用协商成交方式的债券通用质押式回购的申报数量限制",
        "testid": "53.16",
        "交易市场": "上海证券交易所",
        "成交方式": "协商成交",
        "交易类型": "债券通用质押式回购",
        "申报数量": "不为1000元面额或者其整数倍",
        "操作": "申报",
        "结果": "不成功"
    },
    {
        "rule": "53",
        "测试关注点": "债券交易的单笔最大申报数量不得超过100亿元面额",
        "testid": "53.17",
        "交易市场": "上海证券交易所",
        "交易种类": "债券交易",
        "申报数量": "不得超过100亿元面额",
        "操作": "申报",
        "结果": "成功"
    },
    {
        "rule": "53",
        "测试关注点": "债券交易的单笔最大申报数量不得超过100亿元面额",
        "testid": "53.18",
        "交易市场": "上海证券交易所",
        "交易种类": "债券交易",
        "申报数量": "超过100亿元面额",
        "操作": "申报",
        "结果": "不成功"
    },
    {
        "rule": "55",
        "测试关注点": "采用匹配成交方式的债券现券的申报价格最小变动单位",
        "testid": "55.1",
        "交易市场": "上海证券交易所",
        "成交方式": "匹配成交",
        "交易方式": "债券现券",
        "申报价格": "最小变动单位为0.001元",
        "操作": "申报",
        "结果": "成功"
    },
    {
        "rule": "55",
        "测试关注点": "采用匹配成交方式的债券现券的申报价格最小变动单位",
        "testid": "55.2",
        "交易市场": "上海证券交易所",
        "成交方式": "匹配成交",
        "交易方式": "债券现券",
        "申报价格": "最小变动单位不为0.001元",
        "操作": "申报",
        "结果": "不成功"
    },
    {
        "rule": "55",
        "测试关注点": "采用匹配成交方式的债券通用质押式回购的申报价格最小变动单位",
        "testid": "55.3",
        "交易市场": "上海证券交易所",
        "成交方式": "匹配成交",
        "交易方式": "债券通用质押式回购",
        "申报价格": "最小变动单位为0.005元",
        "操作": "申报",
        "结果": "成功"
    },
    {
        "rule": "55",
        "测试关注点": "采用匹配成交方式的债券通用质押式回购的申报价格最小变动单位",
        "testid": "55.4",
        "交易市场": "上海证券交易所",
        "成交方式": "匹配成交",
        "交易方式": "债券通用质押式回购",
        "申报价格": "最小变动单位不是0.005元",
        "操作": "申报",
        "结果": "不成功"
    },
    {
        "rule": "55",
        "测试关注点": "采用匹配成交方式的非债券通用质押式回购且非债券现券的申报价格最小变动单位",
        "testid": "55.5",
        "交易市场": "上海证券交易所",
        "交易方式": "非债券通用质押式回购且非债券现券",
        "成交方式": "匹配成交",
        "申报价格": "最小变动单位为0.0001元",
        "操作": "申报",
        "结果": "成功"
    },
    {
        "rule": "55",
        "测试关注点": "采用匹配成交方式的非债券通用质押式回购且非债券现券的申报价格最小变动单位",
        "testid": "55.6",
        "交易市场": "上海证券交易所",
        "交易方式": "非债券通用质押式回购且非债券现券",
        "成交方式": "匹配成交",
        "申报价格": "最小变动单位不为0.0001元",
        "操作": "申报",
        "结果": "不成功"
    },
    {
        "rule": "59",
        "测试关注点": "用匹配成交方式的债券现券的申报数量限制",
        "testid": "59.1",
        "交易市场": "上海证券交易所",
        "交易类型": "债券现券",
        "成交方式": "匹配成交",
        "是否匿名": "匿名方式",
        "申报数量": "申报数量应当为10万元面额或者其整数倍",
        "操作": "申报买入",
        "前置规则": "53.1,53.17",
        "结果": "成功"
    },
    {
        "rule": "59",
        "测试关注点": "用匹配成交方式的债券现券的申报数量限制",
        "testid": "59.1",
        "交易市场": "上海证券交易所",
        "交易类型": "债券现券",
        "成交方式": "匹配成交",
        "是否匿名": "显名方式",
        "申报数量": "申报数量应当为10万元面额或者其整数倍",
        "操作": "申报买入",
        "前置规则": "53.17,53.1",
        "结果": "不成功"
    },
    {
        "rule": "59",
        "测试关注点": "用匹配成交方式的债券现券的申报数量限制",
        "testid": "59.3",
        "交易市场": "上海证券交易所",
        "交易类型": "债券现券",
        "成交方式": "匹配成交",
        "是否匿名": "匿名方式",
        "申报数量": "卖出时不足10万元面额的部分,应当一次性申报",
        "操作": "申报卖出",
        "前置规则": "53.17,53.1",
        "结果": "成功"
    },
    {
        "rule": "59",
        "测试关注点": "用匹配成交方式的债券现券的申报数量限制",
        "testid": "59.4",
        "交易市场": "上海证券交易所",
        "交易类型": "债券现券",
        "成交方式": "匹配成交",
        "是否匿名": "显名方式",
        "申报数量": "卖出时不足10万元面额的部分,应当一次性申报",
        "操作": "申报卖出",
        "前置规则": "53.17,53.1",
        "结果": "不成功"
    },
    {
        "rule": "59",
        "测试关注点": "用协商成交方式的债券现券的申报数量限制",
        "testid": "53.5",
        "交易市场": "上海证券交易所",
        "成交方式": "协商成交",
        "交易类型": "债券现券",
        "是否匿名": "显名方式",
        "申报数量": "不低于1000元面额,且为100元面额整数倍",
        "操作": "申报",
        "前置规则": "53.17,53.13",
        "结果": "成功"
    },
    {
        "rule": "59",
        "测试关注点": "用协商成交方式的债券现券的申报数量限制",
        "testid": "53.6",
        "交易市场": "上海证券交易所",
        "成交方式": "协商成交",
        "交易类型": "债券现券",
        "是否匿名": "匿名方式",
        "申报数量": "不低于1000元面额,且为100元面额整数倍",
        "操作": "申报",
        "前置规则": "53.17,53.13",
        "结果": "不成功"
    },
    {
        "rule": "59",
        "测试关注点": "用协商成交方式的债券通用质押式回购的申报数量限制",
        "testid": "59.7",
        "交易市场": "上海证券交易所",
        "成交方式": "协商成交",
        "是否匿名": "显名方式",
        "交易类型": "债券通用质押式回购",
        "申报数量": "为1000元面额或者其整数倍",
        "操作": "申报",
        "结果": "成功",
        "前置规则": "53.17,53.13"
    },
    {
        "rule": "59",
        "测试关注点": "用协商成交方式的债券通用质押式回购的申报数量限制",
        "testid": "59.8",
        "交易市场": "上海证券交易所",
        "成交方式": "协商成交",
        "是否匿名": "匿名方式",
        "交易类型": "债券通用质押式回购",
        "申报数量": "为1000元面额或者其整数倍",
        "操作": "申报",
        "结果": "不成功",
        "前置规则": "53.17,53.13"
    },
    {
        "rule": "71",
        "测试关注点": "债券的有效申报价格范围",
        "testid": "71.1",
        "交易市场": "上海证券交易所",
        "交易阶段": "集合匹配阶段",
        "交易品种": "债券",
        "有效申报价格范围": "前收盘价的上下30%",
        "操作": "申报",
        "结果": "成功"
    },
    {
        "rule": "71",
        "测试关注点": "债券的有效申报价格范围",
        "testid": "71.2",
        "交易市场": "上海证券交易所",
        "交易阶段": "集合匹配阶段",
        "交易品种": "债券通用质押式回购",
        "有效申报价格范围": "前收盘价的上下100%",
        "操作": "申报",
        "结果": "成功"
    },
    {
        "rule": "71",
        "测试关注点": "债券的有效申报价格范围",
        "testid": "71.3",
        "交易市场": "上海证券交易所",
        "债券上市首日的前收盘价": "债券的发行价",
        "操作": "申报",
        "结果": "成功"
    },
    {
        "rule": "72",
        "测试关注点": "债券的有效申报价格范围",
        "testid": "72.1",
        "交易市场": "上海证券交易所",
        "交易阶段": "连续匹配阶段",
        "交易品种": "政府债券、政府支持债券、政策性金融债等",
        "有效申报价格范围": "匹配成交最新成交价格的上下10%",
        "操作": "申报",
        "结果": "成功"
    },
    {
        "rule": "72",
        "测试关注点": "债券的有效申报价格范围",
        "testid": "72.2",
        "交易市场": "上海证券交易所",
        "交易阶段": "连续匹配阶段",
        "交易品种": "债券",
        "有效申报价格范围": "匹配成交最新成交价格的上下20%",
        "操作": "申报",
        "结果": "成功"
    },
    {
        "rule": "72",
        "测试关注点": "债券的有效申报价格范围",
        "testid": "72.3",
        "交易市场": "上海证券交易所",
        "交易品种": "债券通用质押式回购",
        "有效申报价格": "不得高于匹配成交最新成交价格100个基点",
        "操作": "申报",
        "结果": "成功"
    }
]